symlearn/__init__.py
symlearn/core/__init__.py
symlearn/core/functions.py
symlearn/core/methods.py
symlearn/core/metrics.py
symlearn/core/node.py
symlearn/core/operators.py
symlearn/core/parameters.py
symlearn/models/__init__.py
symlearn/models/dffp.py
symlearn/models/ffp.py
symlearn/models/gp.py
symlearn/models/ipp.py
symlearn/models/model.py
symlearn-0.1.1.dist-info/LICENSE
symlearn-0.1.1.dist-info/METADATA
symlearn-0.1.1.dist-info/WHEEL
symlearn-0.1.1.dist-info/top_level.txt
symlearn-0.1.1.dist-info/RECORD
