Metadata-Version: 2.1
Name: symlearn
Version: 0.1.1
Summary: Different Population-based Symbolic Regressors
Home-page: https://github.com/aliwimo/symlearn
Author: Mohamed Aliwi
Author-email: aliwimo@gmail.com
License: MIT License
Keywords: python,symbolic,regression,optimization
Platform: UNKNOWN
Classifier: Development Status :: 3 - Alpha
Classifier: Intended Audience :: Developers
Classifier: Intended Audience :: Science/Research
Classifier: License :: OSI Approved :: MIT License
Classifier: Operating System :: MacOS
Classifier: Operating System :: Microsoft :: Windows
Classifier: Operating System :: Unix
Classifier: Programming Language :: Python :: 3
Classifier: Topic :: Software Development :: Libraries
License-File: LICENSE
Requires-Dist: graphviz (==0.16)
Requires-Dist: numpy
